[
  {
    "id": 1,
    "name": "John Smith",
    "experience": "10 years",
    "num_recipes": 50,
    "likes": 1000,
    "image": "https://plus.unsplash.com/premium_photo-1661768360749-b60196445a6d?ixlib=rb-4.0.3&ixid=MnwxMjA3fDB8MHxzZWFyY2h8N3x8Y29va3xlbnwwfHwwfHw%3D&auto=format&fit=crop&w=500&q=60",
    "description": "John Smith is a professional chef with over 10 years of experience. He loves to experiment with new ingredients and techniques to create unique and delicious dishes.",
    "recipes": [
      {
        "recipe_id": 1,
        "name": "Grilled Salmon",
        "ingredients": [
          "4 salmon fillets",
          "1/4 cup soy sauce",
          "1/4 cup honey",
          "2 tablespoons olive oil",
          "1 teaspoon garlic powder"
        ],
        "cooking_method": "1. Mix soy sauce, honey, olive oil, and garlic powder in a bowl. 2. Brush the mixture onto the salmon fillets. 3. Grill the salmon on medium-high heat for 5-6 minutes on each side. 4. Serve hot.",
        "rating": 4.5,
        "favorite": false
      },
      {
        "recipe_id": 2,
        "name": "Roasted Vegetables",
        "ingredients": [
          "2 cups chopped carrots",
          "2 cups chopped broccoli",
          "2 cups chopped cauliflower",
          "2 tablespoons olive oil",
          "1 teaspoon salt"
        ],
        "cooking_method": "1. Preheat the oven to 425°F. 2. Toss the vegetables with olive oil and salt. 3. Spread the vegetables evenly on a baking sheet. 4. Roast in the oven for 20-25 minutes or until the vegetables are tender and slightly browned. 5. Serve hot.",
        "rating": 4.0,
        "favorite": false
      },
      {
        "recipe_id": 3,
        "name": "Chicken Parmesan",
        "ingredients": [
          "4 boneless, skinless chicken breasts",
          "1 cup breadcrumbs",
          "1/2 cup grated Parmesan cheese",
          "1 teaspoon garlic powder",
          "1 teaspoon dried oregano",
          "1 cup marinara sauce",
          "1 cup shredded mozzarella cheese"
        ],
        "cooking_method": "1. Preheat the oven to 375°F. 2. Mix breadcrumbs, Parmesan cheese, garlic powder, and oregano in a bowl. 3. Coat the chicken breasts with the breadcrumb mixture. 4. Place the chicken breasts in a baking dish and pour marinara sauce over the top. 5. Sprinkle shredded mozzarella cheese over the top. 6. Bake in the oven for 25-30 minutes or until the chicken is cooked",
        "rating": 4.0,
        "favorite": false
      }
    ]
  },
  {
    "id": 2,
    "name": "Carlos Ramirez",
    "experience": "12 years",
    "num_recipes": 60,
    "likes": 900,
    "image": "https://images.unsplash.com/photo-1518148750009-25b2522df9c2?ixlib=rb-4.0.3&ixid=MnwxMjA3fDB8MHxzZWFyY2h8Mnx8Y29va2VyfGVufDB8fDB8fA%3D%3D&auto=format&fit=crop&w=500&q=60",
    "description": "Carlos Ramirez is a skilled chef with over 12 years of experience. He loves to experiment with different cuisines and create unique dishes that are bursting with flavor.",
    "recipes": [
      {
        "recipe_id": 1,
        "name": "Chimichurri Steak",
        "ingredients": [
          "1 pound flank steak",
          "1/4 cup olive oil",
          "1/4 cup chopped fresh parsley",
          "2 tablespoons red wine vinegar",
          "2 garlic cloves, minced",
          "1 tablespoon dried oregano",
          "1 teaspoon salt",
          "1/4 teaspoon black pepper"
        ],
        "cooking_method": "1. Preheat the oven to 375°F. 2. Mix breadcrumbs, Parmesan cheese, garlic powder, and oregano in a bowl. 3. Coat the chicken breasts with the breadcrumb mixture. 4. Place the chicken breasts in a baking dish and pour marinara sauce over the top. 5. Sprinkle shredded mozzarella cheese over the top. 6. Bake in the oven for 25-30 minutes or until the chicken is cooked",
        "rating": 4.0,
        "favorite": false
      },
      {
        "recipe_id": 2,
        "name": "Chicken Parmesan",
        "ingredients": [
          "4 boneless, skinless chicken breasts",
          "1 cup breadcrumbs",
          "1/2 cup grated Parmesan cheese",
          "1 teaspoon garlic powder",
          "1 teaspoon dried oregano",
          "1 cup marinara sauce",
          "1 cup shredded mozzarella cheese"
        ],
        "cooking_method": "1. Preheat the oven to 375°F. 2. Mix breadcrumbs, Parmesan cheese, garlic powder, and oregano in a bowl. 3. Coat the chicken breasts with the breadcrumb mixture. 4. Place the chicken breasts in a baking dish and pour marinara sauce over the top. 5. Sprinkle shredded mozzarella cheese over the top. 6. Bake in the oven for 25-30 minutes or until the chicken is cooked",
        "rating": 4.0,
        "favorite": false
      },
      {
        "recipe_id": 3,
        "name": "Chimichurri Steak",
        "ingredients": [
          "1 pound flank steak",
          "1/4 cup olive oil",
          "1/4 cup chopped fresh parsley",
          "2 tablespoons red wine vinegar",
          "2 garlic cloves, minced",
          "1 tablespoon dried oregano",
          "1 teaspoon salt",
          "1/4 teaspoon black pepper"
        ],
        "cooking_method": "1. Preheat the oven to 375°F. 2. Mix breadcrumbs, Parmesan cheese, garlic powder, and oregano in a bowl. 3. Coat the chicken breasts with the breadcrumb mixture. 4. Place the chicken breasts in a baking dish and pour marinara sauce over the top. 5. Sprinkle shredded mozzarella cheese over the top. 6. Bake in the oven for 25-30 minutes or until the chicken is cooked",
        "rating": 4.0,
        "favorite": false
      }
    ]
  },
  {
    "id": 3,
    "name": "Carlos Ramirez",
    "experience": "12 years",
    "num_recipes": 60,
    "likes": 900,
    "image": "https://images.unsplash.com/photo-1581299894007-aaa50297cf16?ixlib=rb-4.0.3&ixid=MnwxMjA3fDB8MHxzZWFyY2h8OXx8Y2hlZnxlbnwwfDF8MHx8&auto=format&fit=crop&w=500&q=60",
    "description": "Carlos Ramirez is a skilled chef with over 12 years of experience. He loves to experiment with different cuisines and create unique dishes that are bursting with flavor.",
    "recipes": [
      {
        "recipe_id": 1,
        "name": "Grilled Salmon",
        "ingredients": [
          "4 salmon fillets",
          "1/4 cup olive oil",
          "2 tablespoons lemon juice",
          "2 cloves garlic, minced",
          "1 tablespoon chopped fresh parsley",
          "1 teaspoon salt",
          "1/4 teaspoon black pepper"
        ],
        "cooking_method": "1. Preheat grill to medium-high heat. 2. Mix olive oil, lemon juice, garlic, parsley, salt, and black pepper in a bowl. 3. Brush the salmon fillets with the olive oil mixture. 4. Place the salmon fillets on the grill skin-side down. 5. Grill for 6-8 minutes or until the salmon is cooked through. 6. Serve with your favorite sides.",
        "rating": 4.5,
        "favorite": true
      },
      {
        "recipe_id": 2,
        "name": "Pesto Pasta",
        "ingredients": [
          "1 pound pasta",
          "1/2 cup pesto sauce",
          "1/2 cup grated Parmesan cheese",
          "1/4 cup pine nuts",
          "2 tablespoons olive oil"
        ],
        "cooking_method": "1. Cook pasta according to package instructions. 2. Reserve 1/4 cup of pasta water, then drain the rest. 3. In a skillet, toast pine nuts over medium heat for 2-3 minutes or until golden brown. 4. Add pesto sauce and reserved pasta water to the skillet and stir to combine. 5. Add the cooked pasta to the skillet and toss to coat. 6. Serve with grated Parmesan cheese and a drizzle of olive oil.",
        "rating": 4.2,
        "favorite": true
      },
      {
        "recipe_id": 3,
        "name": "Beef Stroganoff",
        "ingredients": [
          "1 pound beef sirloin, cut into thin strips",
          "2 tablespoons vegetable oil",
          "1 onion, chopped",
          "2 cloves garlic, minced",
          "1 cup sliced mushrooms",
          "2 tablespoons flour",
          "1 1/2 cups beef broth",
          "1/2 cup sour cream",
          "Salt and pepper to taste"
        ],
        "cooking_method": "1. Heat vegetable oil in a large skillet over medium-high heat. 2. Add beef strips and cook until browned. 3. Add onion, garlic, and mushrooms and sauté for 2-3 minutes or until softened. 4. Sprinkle flour over the mixture and stir to combine. 5. Add beef broth and bring to a boil. 6. Reduce heat and simmer for 10 minutes or until the sauce has thickened. 7. Stir in sour cream and season with salt and pepper. 8. Serve over egg noodles.",
        "rating": 4.3,
        "favorite": false
      }
    ]
  },
  {
    "id": 4,
    "name": "Maria Torres",
    "experience": "8 years",
    "num_recipes": 45,
    "likes": 700,
    "image": "https://images.unsplash.com/photo-1607631568010-a87245c0daf8?ixlib=rb-4.0.3&ixid=MnwxMjA3fDB8MHxzZWFyY2h8MTd8fGNoZWZ8ZW58MHwxfDB8fA%3D%3D&auto=format&fit=crop&w=500&q=60",
    "description": "Maria Torres is a passionate chef with 8 years of experience. She specializes in Mexican cuisine and loves to share her knowledge and recipes with others.",
    "recipes": [
      {
        "recipe_id": 1,
        "name": "Grilled Salmon",
        "ingredients": [
          "4 salmon fillets",
          "1/4 cup olive oil",
          "2 tablespoons lemon juice",
          "2 cloves garlic, minced",
          "1 tablespoon chopped fresh parsley",
          "1 teaspoon salt",
          "1/4 teaspoon black pepper"
        ],
        "cooking_method": "1. Preheat grill to medium-high heat. 2. Mix olive oil, lemon juice, garlic, parsley, salt, and black pepper in a bowl. 3. Brush the salmon fillets with the olive oil mixture. 4. Place the salmon fillets on the grill skin-side down. 5. Grill for 6-8 minutes or until the salmon is cooked through. 6. Serve with your favorite sides.",
        "rating": 4.5,
        "favorite": true
      },
      {
        "recipe_id": 2,
        "name": "Pesto Pasta",
        "ingredients": [
          "1 pound pasta",
          "1/2 cup pesto sauce",
          "1/2 cup grated Parmesan cheese",
          "1/4 cup pine nuts",
          "2 tablespoons olive oil"
        ],
        "cooking_method": "1. Cook pasta according to package instructions. 2. Reserve 1/4 cup of pasta water, then drain the rest. 3. In a skillet, toast pine nuts over medium heat for 2-3 minutes or until golden brown. 4. Add pesto sauce and reserved pasta water to the skillet and stir to combine. 5. Add the cooked pasta to the skillet and toss to coat. 6. Serve with grated Parmesan cheese and a drizzle of olive oil.",
        "rating": 4.2,
        "favorite": true
      },
      {
        "recipe_id": 3,
        "name": "Beef Stroganoff",
        "ingredients": [
          "1 pound beef sirloin, cut into thin strips",
          "2 tablespoons vegetable oil",
          "1 onion, chopped",
          "2 cloves garlic, minced",
          "1 cup sliced mushrooms",
          "2 tablespoons flour",
          "1 1/2 cups beef broth",
          "1/2 cup sour cream",
          "Salt and pepper to taste"
        ],
        "cooking_method": "1. Heat vegetable oil in a large skillet over medium-high heat. 2. Add beef strips and cook until browned. 3. Add onion, garlic, and mushrooms and sauté for 2-3 minutes or until softened. 4. Sprinkle flour over the mixture and stir to combine. 5. Add beef broth and bring to a boil. 6. Reduce heat and simmer for 10 minutes or until the sauce has thickened. 7. Stir in sour cream and season with salt and pepper. 8. Serve over egg noodles.",
        "rating": 4.3,
        "favorite": false
      }
    ]
  },
  {
    "id": 5,
    "name": "John Smith",
    "experience": "12 years",
    "num_recipes": 60,
    "likes": 1200,
    "image": "https://plus.unsplash.com/premium_photo-1661778091956-15dbe6e47442?ixlib=rb-4.0.3&ixid=MnwxMjA3fDB8MHxzZWFyY2h8MTN8fGNoZWZ8ZW58MHwxfDB8fA%3D%3D&auto=format&fit=crop&w=500&q=60",
    "description": "John Smith is a professional chef with 12 years of experience. He specializes in Italian cuisine and has worked in several prestigious restaurants around the world.",
    "recipes": [
      {
        "recipe_id": 1,
        "name": "Grilled Salmon",
        "ingredients": [
          "4 salmon fillets",
          "1/4 cup olive oil",
          "2 tablespoons lemon juice",
          "2 cloves garlic, minced",
          "1 tablespoon chopped fresh parsley",
          "1 teaspoon salt",
          "1/4 teaspoon black pepper"
        ],
        "cooking_method": "1. Preheat grill to medium-high heat. 2. Mix olive oil, lemon juice, garlic, parsley, salt, and black pepper in a bowl. 3. Brush the salmon fillets with the olive oil mixture. 4. Place the salmon fillets on the grill skin-side down. 5. Grill for 6-8 minutes or until the salmon is cooked through. 6. Serve with your favorite sides.",
        "rating": 4.5,
        "favorite": true
      },
      {
        "recipe_id": 2,
        "name": "Pesto Pasta",
        "ingredients": [
          "1 pound pasta",
          "1/2 cup pesto sauce",
          "1/2 cup grated Parmesan cheese",
          "1/4 cup pine nuts",
          "2 tablespoons olive oil"
        ],
        "cooking_method": "1. Cook pasta according to package instructions. 2. Reserve 1/4 cup of pasta water, then drain the rest. 3. In a skillet, toast pine nuts over medium heat for 2-3 minutes or until golden brown. 4. Add pesto sauce and reserved pasta water to the skillet and stir to combine. 5. Add the cooked pasta to the skillet and toss to coat. 6. Serve with grated Parmesan cheese and a drizzle of olive oil.",
        "rating": 4.2,
        "favorite": true
      },
      {
        "recipe_id": 3,
        "name": "Beef Stroganoff",
        "ingredients": [
          "1 pound beef sirloin, cut into thin strips",
          "2 tablespoons vegetable oil",
          "1 onion, chopped",
          "2 cloves garlic, minced",
          "1 cup sliced mushrooms",
          "2 tablespoons flour",
          "1 1/2 cups beef broth",
          "1/2 cup sour cream",
          "Salt and pepper to taste"
        ],
        "cooking_method": "1. Heat vegetable oil in a large skillet over medium-high heat. 2. Add beef strips and cook until browned. 3. Add onion, garlic, and mushrooms and sauté for 2-3 minutes or until softened. 4. Sprinkle flour over the mixture and stir to combine. 5. Add beef broth and bring to a boil. 6. Reduce heat and simmer for 10 minutes or until the sauce has thickened. 7. Stir in sour cream and season with salt and pepper. 8. Serve over egg noodles.",
        "rating": 4.3,
        "favorite": false
      }
    ]
  },
  {
    "id": 6,
    "name": "John Smith",
    "experience": "12 years",
    "num_recipes": 80,
    "likes": 1200,
    "image": "https://images.unsplash.com/photo-1595475038784-bbe439ff41e6?ixlib=rb-4.0.3&ixid=MnwxMjA3fDB8MHxzZWFyY2h8MzB8fGNoZWZ8ZW58MHwxfDB8fA%3D%3D&auto=format&fit=crop&w=500&q=60",
    "description": "John Smith is a seasoned chef with 12 years of experience in the culinary industry. He specializes in Italian cuisine and loves to experiment with new ingredients and flavors.",
    "recipes": [
      {
        "recipe_id": 1,
        "name": "Grilled Salmon",
        "ingredients": [
          "4 salmon fillets",
          "1/4 cup olive oil",
          "2 tablespoons lemon juice",
          "2 cloves garlic, minced",
          "1 tablespoon chopped fresh parsley",
          "1 teaspoon salt",
          "1/4 teaspoon black pepper"
        ],
        "cooking_method": "1. Preheat grill to medium-high heat. 2. Mix olive oil, lemon juice, garlic, parsley, salt, and black pepper in a bowl. 3. Brush the salmon fillets with the olive oil mixture. 4. Place the salmon fillets on the grill skin-side down. 5. Grill for 6-8 minutes or until the salmon is cooked through. 6. Serve with your favorite sides.",
        "rating": 4.5,
        "favorite": true
      },
      {
        "recipe_id": 2,
        "name": "Pesto Pasta",
        "ingredients": [
          "1 pound pasta",
          "1/2 cup pesto sauce",
          "1/2 cup grated Parmesan cheese",
          "1/4 cup pine nuts",
          "2 tablespoons olive oil"
        ],
        "cooking_method": "1. Cook pasta according to package instructions. 2. Reserve 1/4 cup of pasta water, then drain the rest. 3. In a skillet, toast pine nuts over medium heat for 2-3 minutes or until golden brown. 4. Add pesto sauce and reserved pasta water to the skillet and stir to combine. 5. Add the cooked pasta to the skillet and toss to coat. 6. Serve with grated Parmesan cheese and a drizzle of olive oil.",
        "rating": 4.2,
        "favorite": true
      },
      {
        "recipe_id": 3,
        "name": "Beef Stroganoff",
        "ingredients": [
          "1 pound beef sirloin, cut into thin strips",
          "2 tablespoons vegetable oil",
          "1 onion, chopped",
          "2 cloves garlic, minced",
          "1 cup sliced mushrooms",
          "2 tablespoons flour",
          "1 1/2 cups beef broth",
          "1/2 cup sour cream",
          "Salt and pepper to taste"
        ],
        "cooking_method": "1. Heat vegetable oil in a large skillet over medium-high heat. 2. Add beef strips and cook until browned. 3. Add onion, garlic, and mushrooms and sauté for 2-3 minutes or until softened. 4. Sprinkle flour over the mixture and stir to combine. 5. Add beef broth and bring to a boil. 6. Reduce heat and simmer for 10 minutes or until the sauce has thickened. 7. Stir in sour cream and season with salt and pepper. 8. Serve over egg noodles.",
        "rating": 4.3,
        "favorite": false
      }
    ]
  }
] 